{
  "Major": 0,
  "Minor": 1,
  "Patch": 0,
  "PreReleaseTag": "",
  "PreReleaseTagWithDash": "",
  "PreReleaseLabel": "",
  "PreReleaseLabelWithDash": "",
  "PreReleaseNumber": null,
  "WeightedPreReleaseNumber": 60000,
  "BuildMetaData": 7,
  "BuildMetaDataPadded": "0007",
  "FullBuildMetaData": "7.Branch.main.Sha.20b4405a79063281c6a229d94a1245cb9f7f5abd",
  "MajorMinorPatch": "0.1.0",
  "SemVer": "0.1.0",
  "LegacySemVer": "0.1.0",
  "LegacySemVerPadded": "0.1.0",
  "AssemblySemVer": "0.1.0.0",
  "AssemblySemFileVer": "0.1.0.0",
  "FullSemVer": "0.1.0+7",
  "InformationalVersion": "0.1.0+7.Branch.main.Sha.20b4405a79063281c6a229d94a1245cb9f7f5abd",
  "BranchName": "main",
  "EscapedBranchName": "main",
  "Sha": "20b4405a79063281c6a229d94a1245cb9f7f5abd",
  "ShortSha": "20b4405",
  "NuGetVersionV2": "0.1.0",
  "NuGetVersion": "0.1.0",
  "NuGetPreReleaseTagV2": "",
  "NuGetPreReleaseTag": "",
  "VersionSourceSha": "ca5cbf62e5a998f3fef9a2ea9e9e9ad5245beeb8",
  "CommitsSinceVersionSource": 7,
  "CommitsSinceVersionSourcePadded": "0007",
  "UncommittedChanges": 3,
  "CommitDate": "2023-10-05"
}